{
	"child":{
		"description": "banner下方的分类",
		"value": {},
		"type": "list",
		"config": {
			"filter": "list,page"
		}	
	},
	"pro":{
		"description": "产品中心",
		"value": {},
		"type": "list",
		"config": {
			"width":290,
			"height":224
		}
	},
	"team":{
		"description": "产品介绍",
		"value": {},
		"type": "list",
		"config": {
			"width":370,
			"height":414
		}
	},
	"about": {
		"description": "单页面(关于我们)",
		"value": {},
		"type": "page",
		"config": {
			"nav_width":1920,
		    "nav_height":467
		}
	},
	"movadr":{
		"value":"http://player.youku.com/player.php/sid/XNTkyMTM0MzY4/v.swf",
		"description":"视频地址",
		"type":"text"
		},
	"news":{
		"description": "新闻中心",
		"value": {},
		"type": "list",
		"config": {
			"star_only": true			
		}	
	},
	"newss":{
		"description": "图文列表",
		"value": {},
		"type": "list",
		"config": {
			"star_only": true,
			"width":739,
		    "height":414			
		}	
	}
	
}