{
    "slidepics": {
        "value": [
            {
                "title": "banner",
                "image": "images/banner.png",
                "link": "www.baidu.com",
                "description": "banner1"
            }, {
                "title": "banner",
                "image": "images/banner.png",
                "link": "www.baidu.com",
                "description": "banner2"
            }, {
                "title": "banner",
                "image": "images/banner.png",
                "link": "www.baidu.com",
                "description": "banner3"
            }],
        "description": "首页轮播",
        "type": "images",
        "config": {
            "width":  600,
            "height": 388
        }
    },
    "logo": {
        "value":
        {
            "title": "logo",
            "image": "images/logo.png",
            "link": "www.baidu.com",
            "description": "image"
        },
        "description": "logo",
        "type": "image",
        "config": {
            "width": 173,
            "height": 130
        }
    },
    "link": {
        "value": [
            {
                "title": "关于我们",
                "image": "images/about.jpg",
                "link": "www.baidu.com",
                "description": "About us"
            }, {
                "title": "精彩瞬间",
                "image": "images/about.jpg",
                "link": "www.baidu.com",
                "description": "Wonderful moment"
            }, {
                "title": "加盟G宝盆",
                "image": "images/about.jpg",
                "link": "www.baidu.com",
                "description": "Join Gbaopen"
            }, {
                "title": "联系我们",
                "image": "images/about.jpg",
                "link": "www.baidu.com",
                "description": "Contact us"
            }],
        "description": "首页轮播",
        "type": "images",
        "config": {
            "width":  260,
            "height": 100
        }
    },
    "aside_slidepics": {
        "value": [
            {
                "title": "banner",
                "image": "images/asidebanner.png",
                "link": "www.baidu.com",
                "description": "banner1"
            }, {
                "title": "banner",
                "image": "images/asidebanner.png",
                "link": "www.baidu.com",
                "description": "banner2"
            }, {
                "title": "banner",
                "image": "images/asidebanner.png",
                "link": "www.baidu.com",
                "description": "banner3"
            }],
        "description": "首页轮播",
        "type": "images",
        "config": {
            "width":  600,
            "height": 240
        }
    }
}